discotec/__init__.py
discotec/__main__.py
discotec/config.py
discotec/dataset.py
discotec/extract_data.py
discotec/heuristics.py
discotec/infer.py
discotec/inference_utils.py
discotec/label.py
discotec/train.py
discotec/visualize.py
discotec/models/2d_single_label.py
discotec/models/__init__.py
discotec/models/attn.py
discotec/models/base_model.py
discotec/models/unet_1d.py
discotec/resources/beetles_config.yaml
discotec/resources/example.csv
discotec/resources/example.wav
discotec/resources/example_inference_image.png
discotec/resources/using_beetles_on_colab.ipynb
discotec-1.0.4.dist-info/entry_points.txt
discotec-1.0.4.dist-info/LICENSE.txt
discotec-1.0.4.dist-info/WHEEL
discotec-1.0.4.dist-info/METADATA
discotec-1.0.4.dist-info/RECORD
