Metadata-Version: 2.1
Name: discotec
Version: 1.0.4
Summary: discotec classifies sound events within .wav files using machine learning.
Author-email: Kayla Irish <kayla.irish@umontana.edu>, Tommy Colligan <thomas.colligan@umontana.edu>
Project-URL: Home, https://github.com/TravisWheelerLab/disco
